LICENSE
MANIFEST.in
README.md
requirements.txt
setup.py
cloudpath/cloudpath.py
cloudpath.egg-info/PKG-INFO
cloudpath.egg-info/SOURCES.txt
cloudpath.egg-info/dependency_links.txt
cloudpath.egg-info/requires.txt
cloudpath.egg-info/top_level.txt