Metadata-Version: 2.1
Name: cloudpath
Version: 0.2.0
Summary: Optimized pathlib backend for Google Cloud
Home-page: http://github.com/danijar/cloudpath
Classifier: Intended Audience :: Science/Research
Classifier: License :: OSI Approved :: MIT License
Classifier: Programming Language :: Python :: 3
License-File: LICENSE
